flask_flatpages/__init__.py
flask_flatpages/flatpages.py
flask_flatpages/imports.py
flask_flatpages/page.py
flask_flatpages/utils.py
flask_flatpages/parsers/__init__.py
flask_flatpages/parsers/yaml.py
flask_flatpages-0.9.0.dist-info/licenses/LICENSE
flask_flatpages-0.9.0.dist-info/METADATA
flask_flatpages-0.9.0.dist-info/WHEEL
flask_flatpages-0.9.0.dist-info/top_level.txt
flask_flatpages-0.9.0.dist-info/RECORD
