Metadata-Version: 2.4
Name: Flask-FlatPages
Version: 0.9.0
Summary: Provides flat static pages to a Flask application
Author: Simon Sapin, Igor Davydenko, Padraic Calpin
Maintainer-email: Padraic Calpin <itsme@padraic.xyz>
Project-URL: Repository, https://github.com/Flask-FlatPages/Flask-FlatPages
Project-URL: Documentation, https://flask-flatpages.readthedocs.io/en/latest/
Classifier: Environment :: Web Environment
Classifier: Framework :: Flask
Classifier: Intended Audience :: Developers
Classifier: License :: OSI Approved :: BSD License
Classifier: Operating System :: OS Independent
Classifier: Programming Language :: Python
Classifier: Topic :: Internet :: WWW/HTTP :: Dynamic Content
Classifier: Topic :: Software Development :: Libraries :: Python Modules
Classifier: Programming Language :: Python :: 3
Classifier: Programming Language :: Python :: 3.8
Classifier: Programming Language :: Python :: 3.9
Classifier: Programming Language :: Python :: 3.10
Classifier: Programming Language :: Python :: 3.11
Classifier: Programming Language :: Python :: 3.12
Classifier: Programming Language :: Python :: 3.13
Classifier: Programming Language :: Python :: 3.13
Classifier: Programming Language :: Python :: 3.14
Requires-Python: >=3.8
License-File: LICENSE
Requires-Dist: Flask>1.0
Requires-Dist: Jinja2>=2.10.2
Requires-Dist: Markdown>=2.5
Requires-Dist: PyYAML>5.3.1
Provides-Extra: codehilite
Requires-Dist: Pygments>=2.5.2; extra == "codehilite"
Dynamic: license-file
